Workbook

Sheet Léeme
A1: Datos de prueba — Blend Studio
A3: Qué es | B3: Datos ficticios para probar la app (solo proyecto de desarrollo). Las personas y marcas no existen; las fotos son generadas con IA.
A4: Hojas | B4: Clientes · Empleados · Servicios (tarifario) · Productos · Tratamientos · Sesiones
A5: Colores | B5: Texto azul = dato ingresado (se puede editar). Texto negro = fórmula. Texto verde = toma un valor de otra hoja.
A6: Fotos | B6: Carpeta supabase/seed-demo/fotos/ del proyecto (columna «Foto» indica el archivo).
A7: Fecha de referencia | B7: 7 de octubre de 2026 (las sesiones anteriores figuran como completadas).
A9: SUPUESTOS
A10: ITBMS | B10: 0.07
A11: Fuente de precios de servicios | B11: Referencias públicas de salones, barberías y spas en Ciudad de Panamá (Fresha: fresha.com/lp/en/pa-panam%C3%A1; Booksy; sitio del Spa eforea, Hilton Panamá). Rango gama media-alta. Ajustar antes de producción.
A12: Fuente de precios de productos | B12: Estimación propia de costos de proveedor y precios al público en Panamá para marcas profesionales genéricas. Ajustar con las facturas reales.

Sheet Empleados
A1: ID | B1: Nombre | C1: Apellido | D1: Género | E1: Edad | F1: Rol en el sistema | G1: Especialidad | H1: Comisión % | I1: Recibe reservas web | J1: Acceso al sistema | K1: Correo de prueba | L1: Color en agenda | M1: Foto
A2: e01 | B2: Mariela | C2: Castillo | D2: F | E2: 41 | F2: Administrador | G2: Gerente del salón | H2: 0 | I2: No | J2: Sí | K2: mariela.castillo@prueba.blendstudio.test | L2: #C9A15B | M2: fotos/empleados/e01.webp
A3: e02 | B3: Daniela | C3: Herrera | D3: F | E3: 26 | F3: Recepción | G3: Recepcionista | H3: 0 | I3: No | J3: Sí | K3: daniela.herrera@prueba.blendstudio.test | L3: #8E7DBE | M3: fotos/empleados/e02.webp
A4: e03 | B4: Carlos | C4: Méndez | D4: M | E4: 32 | F4: Profesional | G4: Barbero | H4: 0.4 | I4: Sí | J4: Sí | K4: carlos.mendez@prueba.blendstudio.test | L4: #2E86AB | M4: fotos/empleados/e03.webp
A5: e04 | B5: Ana Lucía | C5: Ríos | D5: F | E5: 35 | F5: Profesional | G5: Estilista y colorista | H5: 0.35 | I5: Sí | J5: Sí | K5: ana.rios@prueba.blendstudio.test | L5: #D1495B | M5: fotos/empleados/e04.webp
A6: e05 | B6: Ricardo | C6: Pinzón | D6: M | E6: 29 | F6: Profesional | G6: Estilista de cabello | H6: 0.35 | I6: Sí | J6: No | K6: — | L6: #00798C | M6: fotos/empleados/e05.webp
A7: e06 | B7: Sofía | C7: Delgado | D7: F | E7: 24 | F7: Profesional | G7: Manicurista y pedicurista | H7: 0.3 | I7: Sí | J7: Sí | K7: sofia.delgado@prueba.blendstudio.test | L7: #EDAE49 | M7: fotos/empleados/e06.webp
A8: e07 | B8: Valeria | C8: Núñez | D8: F | E8: 38 | F8: Profesional | G8: Cosmetóloga y pestañista | H8: 0.3 | I8: Sí | J8: Sí | K8: valeria.nunez@prueba.blendstudio.test | L8: #6A994E | M8: fotos/empleados/e07.webp
A9: e08 | B9: Kevin | C9: Araúz | D9: M | E9: 21 | F9: Asistente | G9: Asistente de salón | H9: 0.05 | I9: No | J9: Sí | K9: kevin.arauz@prueba.blendstudio.test | L9: #7D8491 | M9: fotos/empleados/e08.webp

Sheet Clientes
A1: ID | B1: Nombre | C1: Apellido | D1: Género | E1: Fecha de nacimiento | F1: Edad | G1: Teléfono | H1: Correo | I1: Recordatorios por WhatsApp | J1: Permite uso de fotos | K1: Tratamiento activo | L1: Foto
A2: c01 | B2: Gabriela | C2: Sánchez | D2: F | E2: 33677 | F2: =DATEDIF(E2,TODAY(),"Y") -> 34 | G2: +507 6612-4580 | H2: gabriela.sanchez@correo-prueba.test | I2: Sí | J2: Sí | K2: Tratamiento facial para acné | L2: fotos/clientes/c01.webp
A3: c02 | B3: Luis | C3: Batista | D3: M | E3: 30499 | F3: =DATEDIF(E3,TODAY(),"Y") -> 43 | G3: +507 6745-1123 | H3: luis.batista@correo-prueba.test | I3: Sí | J3: Sí | K3: Tratamiento capilar anticaída | L3: fotos/clientes/c02.webp
A4: c03 | B4: Carolina | C4: Vega | D4: F | E4: 35724 | F4: =DATEDIF(E4,TODAY(),"Y") -> 28 | G4: +507 6230-9917 | H4: carolina.vega@correo-prueba.test | I4: Sí | J4: Sí | K4: Despigmentación de manchas (melasma) | L4: fotos/clientes/c03.webp
A5: c04 | B5: Patricia | C5: Morales | D5: F | E5: 29560 | F5: =DATEDIF(E5,TODAY(),"Y") -> 45 | G5: +507 6901-3344 | H5: patricia.morales@correo-prueba.test | I5: No | J5: Sí | K5: Reconstrucción capilar con keratina | L5: fotos/clientes/c04.webp
A6: c05 | B6: Andrés | C6: Quintero | D6: M | E6: 34849 | F6: =DATEDIF(E6,TODAY(),"Y") -> 31 | G6: +507 6378-2201 | H6: andres.quintero@correo-prueba.test | I6: Sí | J6: Sí | K6: — | L6: fotos/clientes/c05.webp
A7: c06 | B7: María José | C7: Guerra | D7: F | E7: 36933 | F7: =DATEDIF(E7,TODAY(),"Y") -> 25 | G7: +507 6455-7810 | H7: maria.guerra@correo-prueba.test | I7: Sí | J7: No | K7: — | L7: fotos/clientes/c06.webp
A8: c07 | B8: Jorge | C8: Samaniego | D8: M | E8: 24368 | F8: =DATEDIF(E8,TODAY(),"Y") -> 60 | G8: +507 6822-0456 | H8: jorge.samaniego@correo-prueba.test | I8: Sí | J8: Sí | K8: — | L8: fotos/clientes/c07.webp
A9: c08 | B9: Isabel | C9: Cedeño | D9: F | E9: 32258 | F9: =DATEDIF(E9,TODAY(),"Y") -> 38 | G9: +507 6119-6632 | H9: isabel.cedeno@correo-prueba.test | I9: Sí | J9: Sí | K9: — | L9: fotos/clientes/c08.webp
A10: c09 | B10: Diego | C10: Tejada | D10: M | E10: 38299 | F10: =DATEDIF(E10,TODAY(),"Y") -> 21 | G10: +507 6587-3390 | H10: diego.tejada@correo-prueba.test | I10: No | J10: Sí | K10: — | L10: fotos/clientes/c09.webp
A11: c10 | B11: Rosa | C11: Jaén | D11: F | E11: 22079 | F11: =DATEDIF(E11,TODAY(),"Y") -> 66 | G11: +507 6290-1178 | H11: rosa.jaen@correo-prueba.test | I11: Sí | J11: No | K11: — | L11: fotos/clientes/c10.webp
A12: c11 | B12: Fernando | C12: Arosemena | D12: M | E12: 28517 | F12: =DATEDIF(E12,TODAY(),"Y") -> 48 | G12: +507 6733-5025 | H12: fernando.arosemena@correo-prueba.test | I12: Sí | J12: Sí | K12: — | L12: fotos/clientes/c11.webp
A13: c12 | B13: Natalia | C13: Pérez | D13: F | E13: 36375 | F13: =DATEDIF(E13,TODAY(),"Y") -> 27 | G13: +507 6044-8261 | H13: natalia.perez@correo-prueba.test | I13: Sí | J13: Sí | K13: — | L13: fotos/clientes/c12.webp
... A21: c20 | B21: Daniela | C21: Ruiz | D21: F | E21: 28004 | F21: =DATEDIF(E21,TODAY(),"Y") -> 50 | G21: +507 6429-6670 | H21: daniela.ruiz@correo-prueba.test | I21: Sí | J21: Sí | K21: — | L21: fotos/clientes/c20.webp

Sheet Servicios
A1: Categoría | B1: Servicio | C1: Duración (min) | D1: Precio de lista (B/.) | E1: Precio con descuento (B/.) | F1: Ahorro % | G1: Precio final (B/.) | H1: ITBMS (B/.) | I1: Total con ITBMS (B/.) | J1: Lo realiza
A2: Barbería | B2: Corte clásico caballero | C2: 30 | D2: 15 | F2: =IF(E2="","",1-E2/D2) | G2: =IF(E2="",D2,E2) -> 15 | H2: =ROUND(G2*'Léeme'!$B$10,2) -> 1.05 | I2: =G2+H2 -> 16.05 | J2: Carlos Méndez
A3: Barbería | B3: Corte fade / degradado | C3: 40 | D3: 18 | F3: =IF(E3="","",1-E3/D3) | G3: =IF(E3="",D3,E3) -> 18 | H3: =ROUND(G3*'Léeme'!$B$10,2) -> 1.26 | I3: =G3+H3 -> 19.26 | J3: Carlos Méndez
A4: Barbería | B4: Perfilado de barba | C4: 20 | D4: 10 | F4: =IF(E4="","",1-E4/D4) | G4: =IF(E4="",D4,E4) -> 10 | H4: =ROUND(G4*'Léeme'!$B$10,2) -> 0.7 | I4: =G4+H4 -> 10.7 | J4: Carlos Méndez
A5: Barbería | B5: Afeitado clásico con navaja y toalla caliente | C5: 30 | D5: 15 | F5: =IF(E5="","",1-E5/D5) | G5: =IF(E5="",D5,E5) -> 15 | H5: =ROUND(G5*'Léeme'!$B$10,2) -> 1.05 | I5: =G5+H5 -> 16.05 | J5: Carlos Méndez
A6: Barbería | B6: Corte y barba | C6: 60 | D6: 25 | E6: 22 | F6: =IF(E6="","",1-E6/D6) -> 0.12 | G6: =IF(E6="",D6,E6) -> 22 | H6: =ROUND(G6*'Léeme'!$B$10,2) -> 1.54 | I6: =G6+H6 -> 23.54 | J6: Carlos Méndez
A7: Barbería | B7: Corte niño (hasta 12 años) | C7: 30 | D7: 12 | F7: =IF(E7="","",1-E7/D7) | G7: =IF(E7="",D7,E7) -> 12 | H7: =ROUND(G7*'Léeme'!$B$10,2) -> 0.84 | I7: =G7+H7 -> 12.84 | J7: Carlos Méndez
A8: Cabello | B8: Corte dama | C8: 45 | D8: 25 | F8: =IF(E8="","",1-E8/D8) | G8: =IF(E8="",D8,E8) -> 25 | H8: =ROUND(G8*'Léeme'!$B$10,2) -> 1.75 | I8: =G8+H8 -> 26.75 | J8: Ana Lucía Ríos, Ricardo Pinzón
A9: Cabello | B9: Lavado y secado (brushing) | C9: 45 | D9: 20 | F9: =IF(E9="","",1-E9/D9) | G9: =IF(E9="",D9,E9) -> 20 | H9: =ROUND(G9*'Léeme'!$B$10,2) -> 1.4 | I9: =G9+H9 -> 21.4 | J9: Ana Lucía Ríos, Ricardo Pinzón
A10: Cabello | B10: Peinado de evento / recogido | C10: 60 | D10: 45 | F10: =IF(E10="","",1-E10/D10) | G10: =IF(E10="",D10,E10) -> 45 | H10: =ROUND(G10*'Léeme'!$B$10,2) -> 3.15 | I10: =G10+H10 -> 48.15 | J10: Ana Lucía Ríos, Ricardo Pinzón
A11: Cabello | B11: Tinte de raíz | C11: 90 | D11: 45 | F11: =IF(E11="","",1-E11/D11) | G11: =IF(E11="",D11,E11) -> 45 | H11: =ROUND(G11*'Léeme'!$B$10,2) -> 3.15 | I11: =G11+H11 -> 48.15 | J11: Ana Lucía Ríos, Ricardo Pinzón
A12: Cabello | B12: Tinte completo | C12: 120 | D12: 65 | F12: =IF(E12="","",1-E12/D12) | G12: =IF(E12="",D12,E12) -> 65 | H12: =ROUND(G12*'Léeme'!$B$10,2) -> 4.55 | I12: =G12+H12 -> 69.55 | J12: Ana Lucía Ríos, Ricardo Pinzón
A13: Cabello | B13: Mechas o balayage | C13: 180 | D13: 120 | E13: 105 | F13: =IF(E13="","",1-E13/D13) -> 0.125 | G13: =IF(E13="",D13,E13) -> 105 | H13: =ROUND(G13*'Léeme'!$B$10,2) -> 7.35 | I13: =G13+H13 -> 112.35 | J13: Ana Lucía Ríos, Ricardo Pinzón
A14: Cabello | B14: Matizado / gloss | C14: 45 | D14: 30 | F14: =IF(E14="","",1-E14/D14) | G14: =IF(E14="",D14,E14) -> 30 | H14: =ROUND(G14*'Léeme'!$B$10,2) -> 2.1 | I14: =G14+H14 -> 32.1 | J14: Ana Lucía Ríos, Ricardo Pinzón
A15: Cabello | B15: Keratina / alisado | C15: 150 | D15: 120 | F15: =IF(E15="","",1-E15/D15) | G15: =IF(E15="",D15,E15) -> 120 | H15: =ROUND(G15*'Léeme'!$B$10,2) -> 8.4 | I15: =G15+H15 -> 128.4 | J15: Ana Lucía Ríos, Ricardo Pinzón
A16: Cabello | B16: Hidratación profunda | C16: 45 | D16: 30 | F16: =IF(E16="","",1-E16/D16) | G16: =IF(E16="",D16,E16) -> 30 | H16: =ROUND(G16*'Léeme'!$B$10,2) -> 2.1 | I16: =G16+H16 -> 32.1 | J16: Ana Lucía Ríos, Ricardo Pinzón
A17: Cabello | B17: Tratamiento capilar anticaída (sesión) | C17: 60 | D17: 55 | F17: =IF(E17="","",1-E17/D17) | G17: =IF(E17="",D17,E17) -> 55 | H17: =ROUND(G17*'Léeme'!$B$10,2) -> 3.85 | I17: =G17+H17 -> 58.85 | J17: Ana Lucía Ríos, Ricardo Pinzón
A18: Uñas | B18: Uñas acrílicas (set completo) | C18: 90 | D18: 40 | F18: =IF(E18="","",1-E18/D18) | G18: =IF(E18="",D18,E18) -> 40 | H18: =ROUND(G18*'Léeme'!$B$10,2) -> 2.8 | I18: =G18+H18 -> 42.8 | J18: Sofía Delgado
A19: Uñas | B19: Relleno de acrílico | C19: 60 | D19: 28 | F19: =IF(E19="","",1-E19/D19) | G19: =IF(E19="",D19,E19) -> 28 | H19: =ROUND(G19*'Léeme'!$B$10,2) -> 1.96 | I19: =G19+H19 -> 29.96 | J19: Sofía Delgado
A20: Uñas | B20: Uñas en gel / polygel | C20: 90 | D20: 45 | F20: =IF(E20="","",1-E20/D20) | G20: =IF(E20="",D20,E20) -> 45 | H20: =ROUND(G20*'Léeme'!$B$10,2) -> 3.15 | I20: =G20+H20 -> 48.15 | J20: Sofía Delgado
A21: Uñas | B21: Nail art (por uña) | C21: 10 | D21: 2 | F21: =IF(E21="","",1-E21/D21) | G21: =IF(E21="",D21,E21) -> 2 | H21: =ROUND(G21*'Léeme'!$B$10,2) -> 0.14 | I21: =G21+H21 -> 2.14 | J21: Sofía Delgado
A22: Uñas | B22: Retiro de acrílico o gel | C22: 30 | D22: 10 | F22: =IF(E22="","",1-E22/D22) | G22: =IF(E22="",D22,E22) -> 10 | H22: =ROUND(G22*'Léeme'!$B$10,2) -> 0.7 | I22: =G22+H22 -> 10.7 | J22: Sofía Delgado
A23: Manicure | B23: Manicure tradicional | C23: 40 | D23: 12 | F23: =IF(E23="","",1-E23/D23) | G23: =IF(E23="",D23,E23) -> 12 | H23: =ROUND(G23*'Léeme'!$B$10,2) -> 0.84 | I23: =G23+H23 -> 12.84 | J23: Sofía Delgado
A24: Manicure | B24: Manicure semipermanente | C24: 50 | D24: 22 | F24: =IF(E24="","",1-E24/D24) | G24: =IF(E24="",D24,E24) -> 22 | H24: =ROUND(G24*'Léeme'!$B$10,2) -> 1.54 | I24: =G24+H24 -> 23.54 | J24: Sofía Delgado
A25: Manicure | B25: Manicure spa | C25: 60 | D25: 25 | F25: =IF(E25="","",1-E25/D25) | G25: =IF(E25="",D25,E25) -> 25 | H25: =ROUND(G25*'Léeme'!$B$10,2) -> 1.75 | I25: =G25+H25 -> 26.75 | J25: Sofía Delgado
... A49: Spa | B49: Masaje relajante | C49: 60 | D49: 65 | F49: =IF(E49="","",1-E49/D49) | G49: =IF(E49="",D49,E49) -> 65 | H49: =ROUND(G49*'Léeme'!$B$10,2) -> 4.55 | I49: =G49+H49 -> 69.55 | J49: Valeria Núñez
A50: Spa | B50: Masaje con piedras calientes | C50: 75 | D50: 85 | E50: 75 | F50: =IF(E50="","",1-E50/D50) -> 0.11764706 | G50: =IF(E50="",D50,E50) -> 75 | H50: =ROUND(G50*'Léeme'!$B$10,2) -> 5.25 | I50: =G50+H50 -> 80.25 | J50: Valeria Núñez
A51: Spa | B51: Masaje descontracturante | C51: 60 | D51: 70 | F51: =IF(E51="","",1-E51/D51) | G51: =IF(E51="",D51,E51) -> 70 | H51: =ROUND(G51*'Léeme'!$B$10,2) -> 4.9 | I51: =G51+H51 -> 74.9 | J51: Valeria Núñez
A52: Spa | B52: Ritual spa (masaje + facial) | C52: 120 | D52: 130 | E52: 115 | F52: =IF(E52="","",1-E52/D52) -> 0.11538462 | G52: =IF(E52="",D52,E52) -> 115 | H52: =ROUND(G52*'Léeme'!$B$10,2) -> 8.05 | I52: =G52+H52 -> 123.05 | J52: Valeria Núñez
A53: Maquillaje | B53: Maquillaje social | C53: 60 | D53: 45 | F53: =IF(E53="","",1-E53/D53) | G53: =IF(E53="",D53,E53) -> 45 | H53: =ROUND(G53*'Léeme'!$B$10,2) -> 3.15 | I53: =G53+H53 -> 48.15 | J53: Ana Lucía Ríos, Valeria Núñez
A54: Maquillaje | B54: Maquillaje de novia (incluye prueba) | C54: 120 | D54: 150 | F54: =IF(E54="","",1-E54/D54) | G54: =IF(E54="",D54,E54) -> 150 | H54: =ROUND(G54*'Léeme'!$B$10,2) -> 10.5 | I54: =G54+H54 -> 160.5 | J54: Ana Lucía Ríos, Valeria Núñez
B55: Total de servicios en el catálogo | C55: =COUNTA(B2:B54) -> 53

Sheet Productos
A1: SKU | B1: Producto | C1: Categoría | D1: Marca (ficticia) | E1: Uso | F1: Costo (B/.) | G1: Precio de venta (B/.) | H1: Margen (B/.) | I1: Margen % | J1: Stock | K1: Stock mínimo | L1: Estado | M1: Valor del inventario a costo (B/.) | N1: Foto
A2: CAB-001 | B2: Champú reparador de argán 300 ml | C2: Cabello | D2: Aurum Care | E2: Venta | F2: 9.5 | G2: 18 | H2: =IF(G2="","",G2-F2) -> 8.5 | I2: =IF(G2="","",(G2-F2)/G2) -> 0.47222222 | J2: 24 | K2: 6 | L2: =IF(J2<=K2,"Stock bajo","Normal") -> Normal | M2: =F2*J2 -> 228 | N2: fotos/productos/CAB-001.webp
A3: CAB-002 | B3: Acondicionador reparador de argán 300 ml | C3: Cabello | D3: Aurum Care | E3: Venta | F3: 9.5 | G3: 18 | H3: =IF(G3="","",G3-F3) -> 8.5 | I3: =IF(G3="","",(G3-F3)/G3) -> 0.47222222 | J3: 20 | K3: 6 | L3: =IF(J3<=K3,"Stock bajo","Normal") -> Normal | M3: =F3*J3 -> 190 | N3: fotos/productos/CAB-002.webp
A4: CAB-003 | B4: Mascarilla capilar de keratina 250 ml | C4: Cabello | D4: Aurum Care | E4: Venta | F4: 12 | G4: 24 | H4: =IF(G4="","",G4-F4) -> 12 | I4: =IF(G4="","",(G4-F4)/G4) -> 0.5 | J4: 15 | K4: 4 | L4: =IF(J4<=K4,"Stock bajo","Normal") -> Normal | M4: =F4*J4 -> 180 | N4: fotos/productos/CAB-003.webp
A5: CAB-004 | B5: Aceite capilar de argán 50 ml | C5: Cabello | D5: Aurum Care | E5: Venta | F5: 8 | G5: 19 | H5: =IF(G5="","",G5-F5) -> 11 | I5: =IF(G5="","",(G5-F5)/G5) -> 0.57894737 | J5: 18 | K5: 5 | L5: =IF(J5<=K5,"Stock bajo","Normal") -> Normal | M5: =F5*J5 -> 144 | N5: fotos/productos/CAB-004.webp
A6: CAB-005 | B6: Protector térmico en spray 150 ml | C6: Cabello | D6: Aurum Care | E6: Venta | F6: 7 | G6: 15 | H6: =IF(G6="","",G6-F6) -> 8 | I6: =IF(G6="","",(G6-F6)/G6) -> 0.53333333 | J6: 14 | K6: 4 | L6: =IF(J6<=K6,"Stock bajo","Normal") -> Normal | M6: =F6*J6 -> 98 | N6: fotos/productos/CAB-005.webp
A7: CAB-006 | B7: Champú matizador violeta 300 ml | C7: Cabello | D7: Aurum Care | E7: Venta | F7: 10 | G7: 20 | H7: =IF(G7="","",G7-F7) -> 10 | I7: =IF(G7="","",(G7-F7)/G7) -> 0.5 | J7: 10 | K7: 4 | L7: =IF(J7<=K7,"Stock bajo","Normal") -> Normal | M7: =F7*J7 -> 100 | N7: fotos/productos/CAB-006.webp
A8: CAB-007 | B8: Sérum anti-frizz 100 ml | C8: Cabello | D8: Aurum Care | E8: Venta | F8: 7.5 | G8: 16 | H8: =IF(G8="","",G8-F8) -> 8.5 | I8: =IF(G8="","",(G8-F8)/G8) -> 0.53125 | J8: 3 | K8: 4 | L8: =IF(J8<=K8,"Stock bajo","Normal") -> Stock bajo | M8: =F8*J8 -> 22.5 | N8: fotos/productos/CAB-007.webp
A9: BAR-001 | B9: Pomada mate 100 g | C9: Barbería | D9: Barber Co. | E9: Venta | F9: 6 | G9: 14 | H9: =IF(G9="","",G9-F9) -> 8 | I9: =IF(G9="","",(G9-F9)/G9) -> 0.57142857 | J9: 16 | K9: 5 | L9: =IF(J9<=K9,"Stock bajo","Normal") -> Normal | M9: =F9*J9 -> 96 | N9: fotos/productos/BAR-001.webp
A10: BAR-002 | B10: Cera de brillo 100 g | C10: Barbería | D10: Barber Co. | E10: Venta | F10: 6 | G10: 14 | H10: =IF(G10="","",G10-F10) -> 8 | I10: =IF(G10="","",(G10-F10)/G10) -> 0.57142857 | J10: 12 | K10: 5 | L10: =IF(J10<=K10,"Stock bajo","Normal") -> Normal | M10: =F10*J10 -> 72 | N10: fotos/productos/BAR-002.webp
A11: BAR-003 | B11: Aceite para barba 30 ml | C11: Barbería | D11: Barber Co. | E11: Venta | F11: 5.5 | G11: 15 | H11: =IF(G11="","",G11-F11) -> 9.5 | I11: =IF(G11="","",(G11-F11)/G11) -> 0.63333333 | J11: 20 | K11: 5 | L11: =IF(J11<=K11,"Stock bajo","Normal") -> Normal | M11: =F11*J11 -> 110 | N11: fotos/productos/BAR-003.webp
A12: BAR-004 | B12: Bálsamo para barba 60 g | C12: Barbería | D12: Barber Co. | E12: Venta | F12: 6 | G12: 15 | H12: =IF(G12="","",G12-F12) -> 9 | I12: =IF(G12="","",(G12-F12)/G12) -> 0.6 | J12: 2 | K12: 4 | L12: =IF(J12<=K12,"Stock bajo","Normal") -> Stock bajo | M12: =F12*J12 -> 12 | N12: fotos/productos/BAR-004.webp
A13: BAR-005 | B13: Bálsamo after shave 100 ml | C13: Barbería | D13: Barber Co. | E13: Venta | F13: 5 | G13: 12 | H13: =IF(G13="","",G13-F13) -> 7 | I13: =IF(G13="","",(G13-F13)/G13) -> 0.58333333 | J13: 11 | K13: 4 | L13: =IF(J13<=K13,"Stock bajo","Normal") -> Normal | M13: =F13*J13 -> 55 | N13: fotos/productos/BAR-005.webp
... A22: UNA-003 | B22: Crema de manos 75 ml | C22: Uñas | D22: Nail Lab | E22: Venta | F22: 3.5 | G22: 10 | H22: =IF(G22="","",G22-F22) -> 6.5 | I22: =IF(G22="","",(G22-F22)/G22) -> 0.65 | J22: 18 | K22: 5 | L22: =IF(J22<=K22,"Stock bajo","Normal") -> Normal | M22: =F22*J22 -> 63 | N22: fotos/productos/UNA-003.webp
A23: INT-001 | B23: Tinte permanente 60 ml | C23: Coloración (uso interno) | D23: Aurum Color | E23: Uso interno | F23: 4.5 | H23: =IF(G23="","",G23-F23) | I23: =IF(G23="","",(G23-F23)/G23) | J23: 60 | K23: 20 | L23: =IF(J23<=K23,"Stock bajo","Normal") -> Normal | M23: =F23*J23 -> 270 | N23: fotos/productos/INT-001.webp
A24: INT-002 | B24: Oxidante 20 vol 1 L | C24: Coloración (uso interno) | D24: Aurum Color | E24: Uso interno | F24: 6 | H24: =IF(G24="","",G24-F24) | I24: =IF(G24="","",(G24-F24)/G24) | J24: 8 | K24: 3 | L24: =IF(J24<=K24,"Stock bajo","Normal") -> Normal | M24: =F24*J24 -> 48 | N24: fotos/productos/INT-002.webp
A25: INT-003 | B25: Decolorante en polvo 500 g | C25: Coloración (uso interno) | D25: Aurum Color | E25: Uso interno | F25: 14 | H25: =IF(G25="","",G25-F25) | I25: =IF(G25="","",(G25-F25)/G25) | J25: 5 | K25: 2 | L25: =IF(J25<=K25,"Stock bajo","Normal") -> Normal | M25: =F25*J25 -> 70 | N25: fotos/productos/INT-003.webp
A26: INT-004 | B26: Tratamiento de keratina 1 L | C26: Tratamientos (uso interno) | D26: Aurum Care | E26: Uso interno | F26: 45 | H26: =IF(G26="","",G26-F26) | I26: =IF(G26="","",(G26-F26)/G26) | J26: 3 | K26: 1 | L26: =IF(J26<=K26,"Stock bajo","Normal") -> Normal | M26: =F26*J26 -> 135 | N26: fotos/productos/INT-004.webp
A27: INT-005 | B27: Cera depilatoria tibia 800 g | C27: Depilación (uso interno) | D27: Verde Botánica | E27: Uso interno | F27: 12 | H27: =IF(G27="","",G27-F27) | I27: =IF(G27="","",(G27-F27)/G27) | J27: 6 | K27: 2 | L27: =IF(J27<=K27,"Stock bajo","Normal") -> Normal | M27: =F27*J27 -> 72 | N27: fotos/productos/INT-005.webp
A28: INT-006 | B28: Adhesivo para pestañas 5 ml | C28: Pestañas (uso interno) | D28: Lash Studio | E28: Uso interno | F28: 9 | H28: =IF(G28="","",G28-F28) | I28: =IF(G28="","",(G28-F28)/G28) | J28: 4 | K28: 2 | L28: =IF(J28<=K28,"Stock bajo","Normal") -> Normal | M28: =F28*J28 -> 36 | N28: fotos/productos/INT-006.webp
A29: INT-007 | B29: Bandeja de extensiones de pestañas | C29: Pestañas (uso interno) | D29: Lash Studio | E29: Uso interno | F29: 8 | H29: =IF(G29="","",G29-F29) | I29: =IF(G29="","",(G29-F29)/G29) | J29: 12 | K29: 4 | L29: =IF(J29<=K29,"Stock bajo","Normal") -> Normal | M29: =F29*J29 -> 96 | N29: fotos/productos/INT-007.webp
A30: INT-008 | B30: Gel exfoliante de cabina 500 ml | C30: Tratamientos (uso interno) | D30: Verde Botánica | E30: Uso interno | F30: 15 | H30: =IF(G30="","",G30-F30) | I30: =IF(G30="","",(G30-F30)/G30) | J30: 4 | K30: 1 | L30: =IF(J30<=K30,"Stock bajo","Normal") -> Normal | M30: =F30*J30 -> 60 | N30: fotos/productos/INT-008.webp
A31: INT-009 | B31: Hojas de afeitar (caja de 100) | C31: Barbería (uso interno) | D31: Barber Co. | E31: Uso interno | F31: 7 | H31: =IF(G31="","",G31-F31) | I31: =IF(G31="","",(G31-F31)/G31) | J31: 10 | K31: 3 | L31: =IF(J31<=K31,"Stock bajo","Normal") -> Normal | M31: =F31*J31 -> 70 | N31: fotos/productos/INT-009.webp
A32: INT-010 | B32: Toallas desechables (paquete de 100) | C32: Insumos (uso interno) | D32: Genérico | E32: Uso interno | F32: 10 | H32: =IF(G32="","",G32-F32) | I32: =IF(G32="","",(G32-F32)/G32) | J32: 7 | K32: 3 | L32: =IF(J32<=K32,"Stock bajo","Normal") -> Normal | M32: =F32*J32 -> 70 | N32: fotos/productos/INT-010.webp
B33: Totales | J33: =SUM(J2:J32) -> 433 | L33: =COUNTIF(L2:L32,"Stock bajo")&" con stock bajo" -> 2 con stock bajo | M33: =SUM(M2:M32) -> 3105.5

Sheet Tratamientos
A1: Cliente | B1: Procedimiento | C1: Profesional | D1: Sesiones | E1: Cada (días) | F1: Precio por sesión (B/.) | G1: Total del plan (B/.) | H1: Fecha de inicio | I1: Completadas | J1: Progreso | K1: Fotos de avance
A2: Gabriela Sánchez | B2: Tratamiento facial para acné | C2: Valeria Núñez | D2: 6 | E2: 14 | F2: 45 | G2: =D2*F2 -> 270 | H2: 46244 | I2: =COUNTIFS(Sesiones!$A:$A,A2,Sesiones!$E:$E,"Completada") -> 5 | J2: =IF(D2=0,0,I2/D2) -> 0.83333333 | K2: fotos/tratamientos/acne-1-antes … -4-despues.webp
A3: Luis Batista | B3: Tratamiento capilar anticaída | C3: Ana Lucía Ríos | D3: 8 | E3: 14 | F3: 55 | G3: =D3*F3 -> 440 | H3: 46204 | I3: =COUNTIFS(Sesiones!$A:$A,A3,Sesiones!$E:$E,"Completada") -> 7 | J3: =IF(D3=0,0,I3/D3) -> 0.875 | K3: fotos/tratamientos/capilar-1-antes … -4-despues.webp
A4: Carolina Vega | B4: Despigmentación de manchas (melasma) | C4: Valeria Núñez | D4: 6 | E4: 21 | F4: 60 | G4: =D4*F4 -> 360 | H4: 46223 | I4: =COUNTIFS(Sesiones!$A:$A,A4,Sesiones!$E:$E,"Completada") -> 4 | J4: =IF(D4=0,0,I4/D4) -> 0.66666667 | K4: fotos/tratamientos/manchas-1-antes … -4-despues.webp
A5: Patricia Morales | B5: Reconstrucción capilar con keratina | C5: Ana Lucía Ríos | D5: 4 | E5: 30 | F5: 85 | G5: =D5*F5 -> 340 | H5: 46218 | I5: =COUNTIFS(Sesiones!$A:$A,A5,Sesiones!$E:$E,"Completada") -> 3 | J5: =IF(D5=0,0,I5/D5) -> 0.75 | K5: fotos/tratamientos/keratina-1-antes … -4-despues.webp

Sheet Sesiones
A1: Cliente | B1: Procedimiento | C1: Sesión | D1: Fecha | E1: Estado | F1: Pago | G1: Foto
A2: =Tratamientos!A2 -> Gabriela Sánchez | B2: =Tratamientos!B2 -> Tratamiento facial para acné | C2: 1 | D2: =Tratamientos!H2 -> 46244 | E2: Completada | F2: Pagada | G2: fotos/tratamientos/acne-1-antes.webp
A3: =Tratamientos!A2 -> Gabriela Sánchez | B3: =Tratamientos!B2 -> Tratamiento facial para acné | C3: 2 | D3: =D2+Tratamientos!E2 -> 46258 | E3: Completada | F3: Pagada | G3: fotos/tratamientos/acne-2-avance.webp
A4: =Tratamientos!A2 -> Gabriela Sánchez | B4: =Tratamientos!B2 -> Tratamiento facial para acné | C4: 3 | D4: =D3+Tratamientos!E2 -> 46272 | E4: Completada | F4: Pagada | G4: —
A5: =Tratamientos!A2 -> Gabriela Sánchez | B5: =Tratamientos!B2 -> Tratamiento facial para acné | C5: 4 | D5: =D4+Tratamientos!E2 -> 46286 | E5: Completada | F5: Pagada | G5: fotos/tratamientos/acne-3-avance.webp
A6: =Tratamientos!A2 -> Gabriela Sánchez | B6: =Tratamientos!B2 -> Tratamiento facial para acné | C6: 5 | D6: =D5+Tratamientos!E2 -> 46300 | E6: Completada | F6: Pagada | G6: —
A7: =Tratamientos!A2 -> Gabriela Sánchez | B7: =Tratamientos!B2 -> Tratamiento facial para acné | C7: 6 | D7: =D6+Tratamientos!E2 -> 46314 | E7: Pendiente | F7: No pagada | G7: —
A8: =Tratamientos!A3 -> Luis Batista | B8: =Tratamientos!B3 -> Tratamiento capilar anticaída | C8: 1 | D8: =Tratamientos!H3 -> 46204 | E8: Completada | F8: Pagada | G8: fotos/tratamientos/capilar-1-antes.webp
A9: =Tratamientos!A3 -> Luis Batista | B9: =Tratamientos!B3 -> Tratamiento capilar anticaída | C9: 2 | D9: =D8+Tratamientos!E3 -> 46218 | E9: Completada | F9: Pagada | G9: —
A10: =Tratamientos!A3 -> Luis Batista | B10: =Tratamientos!B3 -> Tratamiento capilar anticaída | C10: 3 | D10: =D9+Tratamientos!E3 -> 46232 | E10: Completada | F10: Pagada | G10: fotos/tratamientos/capilar-2-avance.webp
A11: =Tratamientos!A3 -> Luis Batista | B11: =Tratamientos!B3 -> Tratamiento capilar anticaída | C11: 4 | D11: =D10+Tratamientos!E3 -> 46246 | E11: Completada | F11: Pagada | G11: —
A12: =Tratamientos!A3 -> Luis Batista | B12: =Tratamientos!B3 -> Tratamiento capilar anticaída | C12: 5 | D12: =D11+Tratamientos!E3 -> 46260 | E12: Completada | F12: Pagada | G12: fotos/tratamientos/capilar-3-avance.webp
A13: =Tratamientos!A3 -> Luis Batista | B13: =Tratamientos!B3 -> Tratamiento capilar anticaída | C13: 6 | D13: =D12+Tratamientos!E3 -> 46274 | E13: Completada | F13: Pagada | G13: —
A14: =Tratamientos!A3 -> Luis Batista | B14: =Tratamientos!B3 -> Tratamiento capilar anticaída | C14: 7 | D14: =D13+Tratamientos!E3 -> 46288 | E14: Completada | F14: Pagada | G14: —
A15: =Tratamientos!A3 -> Luis Batista | B15: =Tratamientos!B3 -> Tratamiento capilar anticaída | C15: 8 | D15: =D14+Tratamientos!E3 -> 46302 | E15: Pendiente | F15: No pagada | G15: —
A16: =Tratamientos!A4 -> Carolina Vega | B16: =Tratamientos!B4 -> Despigmentación de manchas (melasma) | C16: 1 | D16: =Tratamientos!H4 -> 46223 | E16: Completada | F16: Pagada | G16: fotos/tratamientos/manchas-1-antes.webp
A17: =Tratamientos!A4 -> Carolina Vega | B17: =Tratamientos!B4 -> Despigmentación de manchas (melasma) | C17: 2 | D17: =D16+Tratamientos!E4 -> 46244 | E17: Completada | F17: Pagada | G17: fotos/tratamientos/manchas-2-avance.webp
A18: =Tratamientos!A4 -> Carolina Vega | B18: =Tratamientos!B4 -> Despigmentación de manchas (melasma) | C18: 3 | D18: =D17+Tratamientos!E4 -> 46265 | E18: Completada | F18: Pagada | G18: —
A19: =Tratamientos!A4 -> Carolina Vega | B19: =Tratamientos!B4 -> Despigmentación de manchas (melasma) | C19: 4 | D19: =D18+Tratamientos!E4 -> 46286 | E19: Completada | F19: Pagada | G19: fotos/tratamientos/manchas-3-avance.webp
A20: =Tratamientos!A4 -> Carolina Vega | B20: =Tratamientos!B4 -> Despigmentación de manchas (melasma) | C20: 5 | D20: =D19+Tratamientos!E4 -> 46307 | E20: Pendiente | F20: No pagada | G20: —
A21: =Tratamientos!A4 -> Carolina Vega | B21: =Tratamientos!B4 -> Despigmentación de manchas (melasma) | C21: 6 | D21: =D20+Tratamientos!E4 -> 46328 | E21: Pendiente | F21: No pagada | G21: —
A22: =Tratamientos!A5 -> Patricia Morales | B22: =Tratamientos!B5 -> Reconstrucción capilar con keratina | C22: 1 | D22: =Tratamientos!H5 -> 46218 | E22: Completada | F22: Pagada | G22: fotos/tratamientos/keratina-1-antes.webp
A23: =Tratamientos!A5 -> Patricia Morales | B23: =Tratamientos!B5 -> Reconstrucción capilar con keratina | C23: 2 | D23: =D22+Tratamientos!E5 -> 46248 | E23: Completada | F23: Pagada | G23: fotos/tratamientos/keratina-2-avance.webp
A24: =Tratamientos!A5 -> Patricia Morales | B24: =Tratamientos!B5 -> Reconstrucción capilar con keratina | C24: 3 | D24: =D23+Tratamientos!E5 -> 46278 | E24: Completada | F24: Pagada | G24: fotos/tratamientos/keratina-3-avance.webp
A25: =Tratamientos!A5 -> Patricia Morales | B25: =Tratamientos!B5 -> Reconstrucción capilar con keratina | C25: 4 | D25: =D24+Tratamientos!E5 -> 46308 | E25: Pendiente | F25: No pagada | G25: —
